{
  "CallerReference": "50865f0d-30d4-e576-5d4b-b457ac2686c0",
  "Aliases": {
    "Quantity": 0
  },
  "Origins": {
    "Quantity": 1,
    "Items": [
      {
        "Id": "OurChantsFrontendStackWebsiteDistributionOrigin11707423E",
        "DomainName": "ourchants-website.s3.amazonaws.com",
        "OriginPath": "",
        "CustomHeaders": {
          "Quantity": 0
        },
        "S3OriginConfig": {
          "OriginAccessIdentity": ""
        },
        "ConnectionAttempts": 3,
        "ConnectionTimeout": 10,
        "OriginShield": {
          "Enabled": false
        }
      }
    ]
  },
  "OriginGroups": {
    "Quantity": 0
  },
  "DefaultRootObject": "index.html",
  "DefaultCacheBehavior": {
    "TargetOriginId": "OurChantsFrontendStackWebsiteDistributionOrigin11707423E",
    "TrustedSigners": {
      "Enabled": false,
      "Quantity": 0
    },
    "TrustedKeyGroups": {
      "Enabled": false,
      "Quantity": 0
    },
    "ViewerProtocolPolicy": "redirect-to-https",
    "AllowedMethods": {
      "Quantity": 3,
      "Items": [
        "HEAD",
        "GET",
        "OPTIONS"
      ],
      "CachedMethods": {
        "Quantity": 2,
        "Items": [
          "HEAD",
          "GET"
        ]
      }
    },
    "SmoothStreaming": false,
    "Compress": true,
    "LambdaFunctionAssociations": {
      "Quantity": 0
    },
    "FunctionAssociations": {
      "Quantity": 0
    },
    "FieldLevelEncryptionId": "",
    "CachePolicyId": "658327ea-f89d-4fab-a63d-7e88639e58f6",
    "OriginRequestPolicyId": "88a5eaf4-2fd4-4709-b370-b4c650ea3fcf",
    "GrpcConfig": {
      "Enabled": false
    }
  },
  "CacheBehaviors": {
    "Quantity": 0
  },
  "CustomErrorResponses": {
    "Quantity": 2,
    "Items": [
      {
        "ErrorCode": 403,
        "ResponsePagePath": "/index.html",
        "ResponseCode": "200",
        "ErrorCachingMinTTL": 300
      },
      {
        "ErrorCode": 404,
        "ResponsePagePath": "/index.html",
        "ResponseCode": "200",
        "ErrorCachingMinTTL": 300
      }
    ]
  },
  "Comment": "OurChants Website Distribution",
  "Logging": {
    "Enabled": false,
    "IncludeCookies": false,
    "Bucket": "",
    "Prefix": ""
  },
  "PriceClass": "PriceClass_All",
  "Enabled": true,
  "ViewerCertificate": {
    "CloudFrontDefaultCertificate": true,
    "SSLSupportMethod": "vip",
    "MinimumProtocolVersion": "TLSv1",
    "CertificateSource": "cloudfront"
  },
  "Restrictions": {
    "GeoRestriction": {
      "RestrictionType": "none",
      "Quantity": 0
    }
  },
  "WebACLId": "arn:aws:wafv2:us-east-1:418272766513:global/webacl/WebsiteWafAcl-WTSmQXLOsQCX/5805e53a-23f8-4e91-9857-eeb3799edb8e",
  "HttpVersion": "http2",
  "IsIPV6Enabled": true,
  "ContinuousDeploymentPolicyId": "",
  "Staging": false
} 